setup.py
nvm/__init__.py
nvm/libex.py
nvm/pmem.py
nvm/pmemblk.py
nvm/pmemlog.py
nvm/pmemobj/__init__.py
nvm/pmemobj/compat.py
nvm/pmemobj/dict.py
nvm/pmemobj/list.py
nvm/pmemobj/object.py
nvm/pmemobj/pool.py
nvm/pmemobj/set.py
nvm/pmemobj/tuple.py
pynvm.egg-info/PKG-INFO
pynvm.egg-info/SOURCES.txt
pynvm.egg-info/dependency_links.txt
pynvm.egg-info/requires.txt
pynvm.egg-info/top_level.txt
pynvm.egg-info/zip-safe