Metadata-Version: 1.1
Name: pynvm
Version: 0.3.1
Summary: Next-generation non-volatile memory for Python.
Home-page: https://github.com/pmem/pynvm
Author: "Christian S. Perone" <christian.perone@gmail.com>, "R. David Murray" <rdmurray@bitdance.com>, "Catalin G. Manciu" <catalin.gabriel.manciu@intel.com>
Author-email: UNKNOWN
License: BSD 3-clause
Keywords: nvm,scm,non-volatile memory,pmdk,pmem,dax
Platform: Any
Classifier: Development Status :: 4 - Beta
Classifier: Operating System :: OS Independent
Classifier: Programming Language :: Python
Classifier: Topic :: Software Development :: Libraries :: Python Modules
